hawkeslib/__init__.py
hawkeslib/model/__init__.py
hawkeslib/model/model.py
hawkeslib/model/mv_exp.py
hawkeslib/model/poisson.py
hawkeslib/model/uv_bayes.py
hawkeslib/model/uv_exp.py
hawkeslib/model/c/__init__.py
hawkeslib/model/c/c_mv_exp.cpython-36m-darwin.so
hawkeslib/model/c/c_mv_samp.cpython-36m-darwin.so
hawkeslib/model/c/c_uv_bayes.cpython-36m-darwin.so
hawkeslib/model/c/c_uv_exp.cpython-36m-darwin.so
hawkeslib/util/__init__.py
hawkeslib/util/multitrace.py
hawkeslib-0.2.2.dist-info/LICENSE
hawkeslib-0.2.2.dist-info/METADATA
hawkeslib-0.2.2.dist-info/WHEEL
hawkeslib-0.2.2.dist-info/top_level.txt
hawkeslib-0.2.2.dist-info/RECORD
