Metadata-Version: 2.1
Name: hawkeslib
Version: 0.2.2
Summary: parameter estimation for simple Hawkes (self-exciting) processes
Home-page: http://hawkeslib.rtfd.io
Author: Caner Turkmen
Author-email: caner.turkmen@boun.edu.tr
License: MIT
Platform: UNKNOWN
Classifier: Programming Language :: Python
Classifier: Programming Language :: Python :: 2
Classifier: Programming Language :: Cython
Classifier: Development Status :: 3 - Alpha
Classifier: Intended Audience :: Developers
Classifier: Intended Audience :: Science/Research
Classifier: License :: OSI Approved :: MIT License
Classifier: Topic :: Scientific/Engineering
Classifier: Topic :: Scientific/Engineering :: Information Analysis
Requires-Python: >=2.7.5
Requires-Dist: numpy (>=1.14)
Requires-Dist: Cython (>=0.28)
Requires-Dist: scipy (>=1.1)
Requires-Dist: numdifftools (>=0.9)
Provides-Extra: docs
Requires-Dist: Sphinx ; extra == 'docs'
Requires-Dist: sphinx-rtd-theme (>=0.4) ; extra == 'docs'
Provides-Extra: test
Requires-Dist: mock ; extra == 'test'
Requires-Dist: nose ; extra == 'test'
